vupload/__init__.py
vupload/script.py
vupload-0.0.3.dist-info/LICENSE
vupload-0.0.3.dist-info/METADATA
vupload-0.0.3.dist-info/WHEEL
vupload-0.0.3.dist-info/entry_points.txt
vupload-0.0.3.dist-info/top_level.txt
vupload-0.0.3.dist-info/RECORD
