Metadata-Version: 2.1
Name: vupload
Version: 0.0.3
Summary: A CLI tool for VMware's InitiateFileTransferToGuest
Home-page: UNKNOWN
Author: Nicholas Willhite
Author-email: UNKNOWN
License: UNKNOWN
Platform: UNKNOWN
Requires-Dist: vlab-inf-common
Requires-Dist: requests
